{"id":"tag:search.twitter.com,2005:596360298304528384","objectType":"activity","actor":{"objectType":"person","id":"id:twitter.com:2939009789","link":"http://www.twitter.com/nephewsuncle","displayName":"kev","postedTime":"2014-12-24T01:22:36.000Z","image":"https://pbs.twimg.com/profile_images/595058940699910144/ne3epr7g_normal.jpg","summary":"long live niko","links":[{"href":null,"rel":"me"}],"friendsCount":56,"followersCount":85,"listedCount":0,"statusesCount":2999,"twitterTimeZone":null,"verified":false,"utcOffset":null,"preferredUsername":"nephewsuncle","languages":["en"],"location":{"objectType":"place","displayName":"baltimore"},"favoritesCount":197},"verb":"share","postedTime":"2015-05-07T17:05:49.000Z","generator":{"displayName":"Twitter for iPhone","link":"http://twitter.com/download/iphone"},"provider":{"objectType":"service","displayName":"Twitter","link":"http://www.twitter.com"},"link":"http://twitter.com/nephewsuncle/statuses/596360298304528384","body":"RT @Arjunpandey: His Holiness Gyalwang @Drukpa praying with the communities of Baltimore for #Peace &amp; a better #future #FreddieGray http://…","object":{"id":"tag:search.twitter.com,2005:596345563462918144","objectType":"activity","actor":{"objectType":"person","id":"id:twitter.com:16945823","link":"http://www.twitter.com/Arjunpandey","displayName":"Arjunpandey","postedTime":"2008-10-24T08:25:38.000Z","image":"https://pbs.twimg.com/profile_images/3399706811/c1018890f5ad9c8e9ca6407bf21cde38_normal.jpeg","summary":"Adventurer, explorer and documentary film maker","links":[{"href":null,"rel":"me"}],"friendsCount":266,"followersCount":676,"listedCount":6,"statusesCount":965,"twitterTimeZone":"Hawaii","verified":false,"utcOffset":"-36000","preferredUsername":"Arjunpandey","languages":["en"],"location":{"objectType":"place","displayName":"Delhi"},"favoritesCount":115},"verb":"post","postedTime":"2015-05-07T16:07:16.000Z","generator":{"displayName":"iOS","link":"http://www.apple.com"},"provider":{"objectType":"service","displayName":"Twitter","link":"http://www.twitter.com"},"link":"http://twitter.com/Arjunpandey/statuses/596345563462918144","body":"His Holiness Gyalwang @Drukpa praying with the communities of Baltimore for #Peace &amp; a better #future #FreddieGray http://t.co/Hr1ucnEZYQ","object":{"objectType":"note","id":"object:search.twitter.com,2005:596345563462918144","summary":"His Holiness Gyalwang @Drukpa praying with the communities of Baltimore for #Peace &amp; a better #future #FreddieGray http://t.co/Hr1ucnEZYQ","link":"http://twitter.com/Arjunpandey/statuses/596345563462918144","postedTime":"2015-05-07T16:07:16.000Z"},"favoritesCount":4,"twitter_entities":{"hashtags":[{"text":"Peace","indices":[76,82]},{"text":"future","indices":[98,105]},{"text":"FreddieGray","indices":[106,118]}],"trends":[],"urls":[],"user_mentions":[{"screen_name":"Drukpa","name":"Gyalwang Drukpa","id":42865272,"id_str":"42865272","indices":[22,29]}],"symbols":[],"media":[{"id":596345563332943873,"id_str":"596345563332943873","indices":[119,141],"media_url":"http://pbs.twimg.com/media/CEalIVnXIAEpvDO.jpg","media_url_https":"https://pbs.twimg.com/media/CEalIVnXIAEpvDO.jpg","url":"http://t.co/Hr1ucnEZYQ","display_url":"pic.twitter.com/Hr1ucnEZYQ","expanded_url":"http://twitter.com/Arjunpandey/status/596345563462918144/photo/1","type":"photo","sizes":{"small":{"w":340,"h":255,"resize":"fit"},"medium":{"w":600,"h":450,"resize":"fit"},"thumb":{"w":150,"h":150,"resize":"crop"},"large":{"w":958,"h":719,"resize":"fit"}}}]},"twitter_extended_entities":{"media":[{"id":596345563332943873,"id_str":"596345563332943873","indices":[119,141],"media_url":"http://pbs.twimg.com/media/CEalIVnXIAEpvDO.jpg","media_url_https":"https://pbs.twimg.com/media/CEalIVnXIAEpvDO.jpg","url":"http://t.co/Hr1ucnEZYQ","display_url":"pic.twitter.com/Hr1ucnEZYQ","expanded_url":"http://twitter.com/Arjunpandey/status/596345563462918144/photo/1","type":"photo","sizes":{"small":{"w":340,"h":255,"resize":"fit"},"medium":{"w":600,"h":450,"resize":"fit"},"thumb":{"w":150,"h":150,"resize":"crop"},"large":{"w":958,"h":719,"resize":"fit"}}}]},"twitter_filter_level":"low","twitter_lang":"en"},"favoritesCount":0,"twitter_entities":{"hashtags":[{"text":"Peace","indices":[93,99]},{"text":"future","indices":[115,122]},{"text":"FreddieGray","indices":[123,135]}],"trends":[],"urls":[],"user_mentions":[{"screen_name":"Arjunpandey","name":"Arjunpandey","id":16945823,"id_str":"16945823","indices":[3,15]},{"screen_name":"Drukpa","name":"Gyalwang Drukpa","id":42865272,"id_str":"42865272","indices":[39,46]}],"symbols":[],"media":[{"id":596345563332943873,"id_str":"596345563332943873","indices":[143,144],"media_url":"http://pbs.twimg.com/media/CEalIVnXIAEpvDO.jpg","media_url_https":"https://pbs.twimg.com/media/CEalIVnXIAEpvDO.jpg","url":"http://t.co/Hr1ucnEZYQ","display_url":"pic.twitter.com/Hr1ucnEZYQ","expanded_url":"http://twitter.com/Arjunpandey/status/596345563462918144/photo/1","type":"photo","sizes":{"small":{"w":340,"h":255,"resize":"fit"},"medium":{"w":600,"h":450,"resize":"fit"},"thumb":{"w":150,"h":150,"resize":"crop"},"large":{"w":958,"h":719,"resize":"fit"}},"source_status_id":596345563462918144,"source_status_id_str":"596345563462918144"}]},"twitter_extended_entities":{"media":[{"id":596345563332943873,"id_str":"596345563332943873","indices":[143,144],"media_url":"http://pbs.twimg.com/media/CEalIVnXIAEpvDO.jpg","media_url_https":"https://pbs.twimg.com/media/CEalIVnXIAEpvDO.jpg","url":"http://t.co/Hr1ucnEZYQ","display_url":"pic.twitter.com/Hr1ucnEZYQ","expanded_url":"http://twitter.com/Arjunpandey/status/596345563462918144/photo/1","type":"photo","sizes":{"small":{"w":340,"h":255,"resize":"fit"},"medium":{"w":600,"h":450,"resize":"fit"},"thumb":{"w":150,"h":150,"resize":"crop"},"large":{"w":958,"h":719,"resize":"fit"}},"source_status_id":596345563462918144,"source_status_id_str":"596345563462918144"}]},"twitter_filter_level":"low","twitter_lang":"en","retweetCount":12,"gnip":{"matching_rules":[{"value":"profile_bounding_box:[-77.027094 39.094659 -76.567094 39.444659] sample:25","tag":null}],"urls":[{"url":"http://t.co/Hr1ucnEZYQ","expanded_url":"http://twitter.com/Arjunpandey/status/596345563462918144/photo/1","expanded_status":200}],"language":{"value":"en"},"profileLocations":[{"objectType":"place","geo":{"type":"point","coordinates":[-76.61219,39.29038]},"address":{"country":"United States","countryCode":"US","locality":"Baltimore","region":"Maryland","subRegion":"City of Baltimore"},"displayName":"Baltimore, Maryland, United States"}]}}
{"id":"tag:search.twitter.com,2005:596413271105740800","objectType":"activity","actor":{"objectType":"person","id":"id:twitter.com:991126873","link":"http://www.twitter.com/KashaanMuhammad","displayName":"Kashaan Muhammad","postedTime":"2012-12-05T14:58:36.000Z","image":"https://pbs.twimg.com/profile_images/378800000673524826/c1e134c4e3f37c448660cc66538fc77c_normal.jpeg","summary":"IF WE FOCUS ON BUILDING OUR A.R.K., BLESSING WILL FLOW!!! ( A.R.K.=A RANDOM ACT OF KINDNESS) Sharing info 2 hopefully n prayerfully save a life, FAMILY  FIRST","links":[{"href":"http://noi.org","rel":"me"}],"friendsCount":2002,"followersCount":1329,"listedCount":7,"statusesCount":9424,"twitterTimeZone":"Eastern Time (US & Canada)","verified":false,"utcOffset":"-14400","preferredUsername":"KashaanMuhammad","languages":["en"],"location":{"objectType":"place","displayName":"Annapolis, Maryland"},"favoritesCount":1548},"verb":"share","postedTime":"2015-05-07T20:36:19.000Z","generator":{"displayName":"Twitter for iPhone","link":"http://twitter.com/download/iphone"},"provider":{"objectType":"service","displayName":"Twitter","link":"http://www.twitter.com"},"link":"http://twitter.com/KashaanMuhammad/statuses/596413271105740800","body":"RT @TheFinalCall: Scenes from weekend of reporting by @RMFinalCall in #BaltimoreUprising: http://t.co/AOY1YVojP0 http://t.co/JDAy7PlvYC","object":{"id":"tag:search.twitter.com,2005:596411168048095233","objectType":"activity","actor":{"objectType":"person","id":"id:twitter.com:35490978","link":"http://www.twitter.com/TheFinalCall","displayName":"The Final Call News","postedTime":"2009-04-26T15:46:41.000Z","image":"https://pbs.twimg.com/profile_images/592910055097430017/SyYJ6NBY_normal.jpg","summary":"The Final Call Newspaper is known for hard-hitting and uncompromised reporting. Founded by Minister @LouisFarrakhan. Visit @ http://www.finalcall.com","links":[{"href":"http://www.finalcall.com","rel":"me"}],"friendsCount":37,"followersCount":36488,"listedCount":408,"statusesCount":23118,"twitterTimeZone":"Eastern Time (US & Canada)","verified":false,"utcOffset":"-14400","preferredUsername":"TheFinalCall","languages":["en"],"location":{"objectType":"place","displayName":"Chicago, IL USA"},"favoritesCount":7},"verb":"post","postedTime":"2015-05-07T20:27:57.000Z","generator":{"displayName":"TweetDeck","link":"https://about.twitter.com/products/tweetdeck"},"provider":{"objectType":"service","displayName":"Twitter","link":"http://www.twitter.com"},"link":"http://twitter.com/TheFinalCall/statuses/596411168048095233","body":"Scenes from weekend of reporting by @RMFinalCall in #BaltimoreUprising: http://t.co/AOY1YVojP0 http://t.co/JDAy7PlvYC","object":{"objectType":"note","id":"object:search.twitter.com,2005:596411168048095233","summary":"Scenes from weekend of reporting by @RMFinalCall in #BaltimoreUprising: http://t.co/AOY1YVojP0 http://t.co/JDAy7PlvYC","link":"http://twitter.com/TheFinalCall/statuses/596411168048095233","postedTime":"2015-05-07T20:27:57.000Z"},"favoritesCount":3,"twitter_entities":{"hashtags":[{"text":"BaltimoreUprising","indices":[52,70]}],"trends":[],"urls":[{"url":"http://t.co/AOY1YVojP0","expanded_url":"http://www.finalcall.com/artman/publish/straightwords/article_102309.shtml","display_url":"finalcall.com/artman/publish…","indices":[72,94]}],"user_mentions":[{"screen_name":"RMFinalCall","name":"Richard Muhammad","id":33321491,"id_str":"33321491","indices":[36,48]}],"symbols":[],"media":[{"id":596411157822480385,"id_str":"596411157822480385","indices":[95,117],"media_url":"http://pbs.twimg.com/media/CEbgycIWoAEZsD8.jpg","media_url_https":"https://pbs.twimg.com/media/CEbgycIWoAEZsD8.jpg","url":"http://t.co/JDAy7PlvYC","display_url":"pic.twitter.com/JDAy7PlvYC","expanded_url":"http://twitter.com/TheFinalCall/status/596411168048095233/photo/1","type":"photo","sizes":{"small":{"w":340,"h":255,"resize":"fit"},"medium":{"w":600,"h":450,"resize":"fit"},"thumb":{"w":150,"h":150,"resize":"crop"},"large":{"w":1024,"h":768,"resize":"fit"}}}]},"twitter_extended_entities":{"media":[{"id":596411157822480385,"id_str":"596411157822480385","indices":[95,117],"media_url":"http://pbs.twimg.com/media/CEbgycIWoAEZsD8.jpg","media_url_https":"https://pbs.twimg.com/media/CEbgycIWoAEZsD8.jpg","url":"http://t.co/JDAy7PlvYC","display_url":"pic.twitter.com/JDAy7PlvYC","expanded_url":"http://twitter.com/TheFinalCall/status/596411168048095233/photo/1","type":"photo","sizes":{"small":{"w":340,"h":255,"resize":"fit"},"medium":{"w":600,"h":450,"resize":"fit"},"thumb":{"w":150,"h":150,"resize":"crop"},"large":{"w":1024,"h":768,"resize":"fit"}}}]},"twitter_filter_level":"low","twitter_lang":"en"},"favoritesCount":0,"twitter_entities":{"hashtags":[{"text":"BaltimoreUprising","indices":[70,88]}],"trends":[],"urls":[{"url":"http://t.co/AOY1YVojP0","expanded_url":"http://www.finalcall.com/artman/publish/straightwords/article_102309.shtml","display_url":"finalcall.com/artman/publish…","indices":[90,112]}],"user_mentions":[{"screen_name":"TheFinalCall","name":"The Final Call News","id":35490978,"id_str":"35490978","indices":[3,16]},{"screen_name":"RMFinalCall","name":"Richard Muhammad","id":33321491,"id_str":"33321491","indices":[54,66]}],"symbols":[],"media":[{"id":596411157822480385,"id_str":"596411157822480385","indices":[113,135],"media_url":"http://pbs.twimg.com/media/CEbgycIWoAEZsD8.jpg","media_url_https":"https://pbs.twimg.com/media/CEbgycIWoAEZsD8.jpg","url":"http://t.co/JDAy7PlvYC","display_url":"pic.twitter.com/JDAy7PlvYC","expanded_url":"http://twitter.com/TheFinalCall/status/596411168048095233/photo/1","type":"photo","sizes":{"small":{"w":340,"h":255,"resize":"fit"},"medium":{"w":600,"h":450,"resize":"fit"},"thumb":{"w":150,"h":150,"resize":"crop"},"large":{"w":1024,"h":768,"resize":"fit"}},"source_status_id":596411168048095233,"source_status_id_str":"596411168048095233"}]},"twitter_extended_entities":{"media":[{"id":596411157822480385,"id_str":"596411157822480385","indices":[113,135],"media_url":"http://pbs.twimg.com/media/CEbgycIWoAEZsD8.jpg","media_url_https":"https://pbs.twimg.com/media/CEbgycIWoAEZsD8.jpg","url":"http://t.co/JDAy7PlvYC","display_url":"pic.twitter.com/JDAy7PlvYC","expanded_url":"http://twitter.com/TheFinalCall/status/596411168048095233/photo/1","type":"photo","sizes":{"small":{"w":340,"h":255,"resize":"fit"},"medium":{"w":600,"h":450,"resize":"fit"},"thumb":{"w":150,"h":150,"resize":"crop"},"large":{"w":1024,"h":768,"resize":"fit"}},"source_status_id":596411168048095233,"source_status_id_str":"596411168048095233"}]},"twitter_filter_level":"low","twitter_lang":"en","retweetCount":10,"gnip":{"matching_rules":[{"value":"profile_bounding_box:[-76.567094 38.744659 -76.107094 39.094659] sample:25","tag":null}],"urls":[{"url":"http://t.co/JDAy7PlvYC","expanded_url":"http://twitter.com/TheFinalCall/status/596411168048095233/photo/1","expanded_status":200},{"url":"http://t.co/AOY1YVojP0","expanded_url":"http://www.finalcall.com/artman/publish/straightwords/article_102309.shtml","expanded_status":200}],"language":{"value":"en"},"profileLocations":[{"objectType":"place","geo":{"type":"point","coordinates":[-76.49218,38.97845]},"address":{"country":"United States","countryCode":"US","locality":"Annapolis","region":"Maryland","subRegion":"Anne Arundel County"},"displayName":"Annapolis, Maryland, United States"}]}}
{"id":"tag:search.twitter.com,2005:596490732342550528","objectType":"activity","actor":{"objectType":"person","id":"id:twitter.com:29143696","link":"http://www.twitter.com/Ms_ESPN87","displayName":"Sierra Teresa","postedTime":"2009-04-06T04:31:22.000Z","image":"https://pbs.twimg.com/profile_images/584860690143293440/bB7Sl0Cw_normal.jpg","summary":"The EAGLES and LEBRON are all that matters. AKA since 07","links":[{"href":"http://Instagram.com/sierra_teresa","rel":"me"}],"friendsCount":468,"followersCount":623,"listedCount":12,"statusesCount":93147,"twitterTimeZone":"Eastern Time (US & Canada)","verified":false,"utcOffset":"-14400","preferredUsername":"Ms_ESPN87","languages":["en"],"location":{"objectType":"place","displayName":"Philly "},"favoritesCount":383},"verb":"share","postedTime":"2015-05-08T01:44:07.000Z","generator":{"displayName":"TweetCaster for Android","link":"http://www.tweetcaster.com"},"provider":{"objectType":"service","displayName":"Twitter","link":"http://www.twitter.com"},"link":"http://twitter.com/Ms_ESPN87/statuses/596490732342550528","body":"RT @JunaeBrown: Such an amazing conversation!!! The time is now. #BETBaltimoreSpeaks #Currently #BaltimoreUprising #FreddieGray http://t.co…","object":{"id":"tag:search.twitter.com,2005:596489627604779008","objectType":"activity","actor":{"objectType":"person","id":"id:twitter.com:43782334","link":"http://www.twitter.com/JunaeBrown","displayName":"Ms.Brown","postedTime":"2009-05-31T23:47:54.000Z","image":"https://pbs.twimg.com/profile_images/564294241724399616/7uqqHkh4_normal.jpeg","summary":"Even with its rough edges, a cactus in the middle of the night, can bloom the perfect flower. |Sony Music @ColumbiaRecords| #4EverTae","links":[{"href":"http://Instagram.com/JunaeBrown","rel":"me"}],"friendsCount":313,"followersCount":1166,"listedCount":21,"statusesCount":64665,"twitterTimeZone":"Quito","verified":false,"utcOffset":"-18000","preferredUsername":"JunaeBrown","languages":["en"],"location":{"objectType":"place","displayName":"NaeYork City  "},"favoritesCount":1117},"verb":"post","postedTime":"2015-05-08T01:39:44.000Z","generator":{"displayName":"Twitter for iPhone","link":"http://twitter.com/download/iphone"},"provider":{"objectType":"service","displayName":"Twitter","link":"http://www.twitter.com"},"link":"http://twitter.com/JunaeBrown/statuses/596489627604779008","body":"Such an amazing conversation!!! The time is now. #BETBaltimoreSpeaks #Currently #BaltimoreUprising #FreddieGray http://t.co/mYawkO75NA","object":{"objectType":"note","id":"object:search.twitter.com,2005:596489627604779008","summary":"Such an amazing conversation!!! The time is now. #BETBaltimoreSpeaks #Currently #BaltimoreUprising #FreddieGray http://t.co/mYawkO75NA","link":"http://twitter.com/JunaeBrown/statuses/596489627604779008","postedTime":"2015-05-08T01:39:44.000Z"},"favoritesCount":11,"twitter_entities":{"hashtags":[{"text":"BETBaltimoreSpeaks","indices":[49,68]},{"text":"Currently","indices":[69,79]},{"text":"BaltimoreUprising","indices":[80,98]},{"text":"FreddieGray","indices":[99,111]}],"trends":[],"urls":[],"user_mentions":[],"symbols":[],"media":[{"id":596489182257741824,"id_str":"596489182257741824","indices":[112,134],"media_url":"http://pbs.twimg.com/media/CEcnwDzWAAALfF7.jpg","media_url_https":"https://pbs.twimg.com/media/CEcnwDzWAAALfF7.jpg","url":"http://t.co/mYawkO75NA","display_url":"pic.twitter.com/mYawkO75NA","expanded_url":"http://twitter.com/JunaeBrown/status/596489627604779008/photo/1","type":"photo","sizes":{"small":{"w":340,"h":453,"resize":"fit"},"medium":{"w":600,"h":800,"resize":"fit"},"thumb":{"w":150,"h":150,"resize":"crop"},"large":{"w":768,"h":1024,"resize":"fit"}}}]},"twitter_extended_entities":{"media":[{"id":596489182257741824,"id_str":"596489182257741824","indices":[112,134],"media_url":"http://pbs.twimg.com/media/CEcnwDzWAAALfF7.jpg","media_url_https":"https://pbs.twimg.com/media/CEcnwDzWAAALfF7.jpg","url":"http://t.co/mYawkO75NA","display_url":"pic.twitter.com/mYawkO75NA","expanded_url":"http://twitter.com/JunaeBrown/status/596489627604779008/photo/1","type":"photo","sizes":{"small":{"w":340,"h":453,"resize":"fit"},"medium":{"w":600,"h":800,"resize":"fit"},"thumb":{"w":150,"h":150,"resize":"crop"},"large":{"w":768,"h":1024,"resize":"fit"}}},{"id":596489182467469312,"id_str":"596489182467469312","indices":[112,134],"media_url":"http://pbs.twimg.com/media/CEcnwElWMAA-8BC.jpg","media_url_https":"https://pbs.twimg.com/media/CEcnwElWMAA-8BC.jpg","url":"http://t.co/mYawkO75NA","display_url":"pic.twitter.com/mYawkO75NA","expanded_url":"http://twitter.com/JunaeBrown/status/596489627604779008/photo/1","type":"photo","sizes":{"small":{"w":340,"h":453,"resize":"fit"},"medium":{"w":600,"h":800,"resize":"fit"},"thumb":{"w":150,"h":150,"resize":"crop"},"large":{"w":768,"h":1024,"resize":"fit"}}},{"id":596489182652047360,"id_str":"596489182652047360","indices":[112,134],"media_url":"http://pbs.twimg.com/media/CEcnwFRWoAAQvZC.jpg","media_url_https":"https://pbs.twimg.com/media/CEcnwFRWoAAQvZC.jpg","url":"http://t.co/mYawkO75NA","display_url":"pic.twitter.com/mYawkO75NA","expanded_url":"http://twitter.com/JunaeBrown/status/596489627604779008/photo/1","type":"photo","sizes":{"small":{"w":340,"h":453,"resize":"fit"},"medium":{"w":600,"h":800,"resize":"fit"},"thumb":{"w":150,"h":150,"resize":"crop"},"large":{"w":768,"h":1024,"resize":"fit"}}}]},"twitter_filter_level":"low","twitter_lang":"en"},"favoritesCount":0,"twitter_entities":{"hashtags":[{"text":"BETBaltimoreSpeaks","indices":[65,84]},{"text":"Currently","indices":[85,95]},{"text":"BaltimoreUprising","indices":[96,114]},{"text":"FreddieGray","indices":[115,127]}],"trends":[],"urls":[],"user_mentions":[{"screen_name":"JunaeBrown","name":"Ms.Brown","id":43782334,"id_str":"43782334","indices":[3,14]}],"symbols":[],"media":[{"id":596489182257741824,"id_str":"596489182257741824","indices":[139,140],"media_url":"http://pbs.twimg.com/media/CEcnwDzWAAALfF7.jpg","media_url_https":"https://pbs.twimg.com/media/CEcnwDzWAAALfF7.jpg","url":"http://t.co/mYawkO75NA","display_url":"pic.twitter.com/mYawkO75NA","expanded_url":"http://twitter.com/JunaeBrown/status/596489627604779008/photo/1","type":"photo","sizes":{"small":{"w":340,"h":453,"resize":"fit"},"medium":{"w":600,"h":800,"resize":"fit"},"thumb":{"w":150,"h":150,"resize":"crop"},"large":{"w":768,"h":1024,"resize":"fit"}},"source_status_id":596489627604779008,"source_status_id_str":"596489627604779008"}]},"twitter_extended_entities":{"media":[{"id":596489182257741824,"id_str":"596489182257741824","indices":[139,140],"media_url":"http://pbs.twimg.com/media/CEcnwDzWAAALfF7.jpg","media_url_https":"https://pbs.twimg.com/media/CEcnwDzWAAALfF7.jpg","url":"http://t.co/mYawkO75NA","display_url":"pic.twitter.com/mYawkO75NA","expanded_url":"http://twitter.com/JunaeBrown/status/596489627604779008/photo/1","type":"photo","sizes":{"small":{"w":340,"h":453,"resize":"fit"},"medium":{"w":600,"h":800,"resize":"fit"},"thumb":{"w":150,"h":150,"resize":"crop"},"large":{"w":768,"h":1024,"resize":"fit"}},"source_status_id":596489627604779008,"source_status_id_str":"596489627604779008"},{"id":596489182467469312,"id_str":"596489182467469312","indices":[139,140],"media_url":"http://pbs.twimg.com/media/CEcnwElWMAA-8BC.jpg","media_url_https":"https://pbs.twimg.com/media/CEcnwElWMAA-8BC.jpg","url":"http://t.co/mYawkO75NA","display_url":"pic.twitter.com/mYawkO75NA","expanded_url":"http://twitter.com/JunaeBrown/status/596489627604779008/photo/1","type":"photo","sizes":{"small":{"w":340,"h":453,"resize":"fit"},"medium":{"w":600,"h":800,"resize":"fit"},"thumb":{"w":150,"h":150,"resize":"crop"},"large":{"w":768,"h":1024,"resize":"fit"}},"source_status_id":596489627604779008,"source_status_id_str":"596489627604779008"},{"id":596489182652047360,"id_str":"596489182652047360","indices":[139,140],"media_url":"http://pbs.twimg.com/media/CEcnwFRWoAAQvZC.jpg","media_url_https":"https://pbs.twimg.com/media/CEcnwFRWoAAQvZC.jpg","url":"http://t.co/mYawkO75NA","display_url":"pic.twitter.com/mYawkO75NA","expanded_url":"http://twitter.com/JunaeBrown/status/596489627604779008/photo/1","type":"photo","sizes":{"small":{"w":340,"h":453,"resize":"fit"},"medium":{"w":600,"h":800,"resize":"fit"},"thumb":{"w":150,"h":150,"resize":"crop"},"large":{"w":768,"h":1024,"resize":"fit"}},"source_status_id":596489627604779008,"source_status_id_str":"596489627604779008"}]},"twitter_filter_level":"low","twitter_lang":"en","retweetCount":10,"gnip":{"matching_rules":[{"value":"profile_bounding_box:[-75.376043 39.848905 -74.909043 40.198905] sample:25","tag":null}],"urls":[{"url":"http://t.co/mYawkO75NA","expanded_url":"http://twitter.com/JunaeBrown/status/596489627604779008/photo/1","expanded_status":200}],"language":{"value":"en"},"profileLocations":[{"objectType":"place","geo":{"type":"point","coordinates":[-75.16379,39.95234]},"address":{"country":"United States","countryCode":"US","locality":"Philadelphia","region":"Pennsylvania","subRegion":"Philadelphia County"},"displayName":"Philadelphia, Pennsylvania, United States"}]}}
{"id":"tag:search.twitter.com,2005:596494331881463808","objectType":"activity","actor":{"objectType":"person","id":"id:twitter.com:71082732","link":"http://www.twitter.com/djolder","displayName":"Daniel José Older","postedTime":"2009-09-02T21:35:18.000Z","image":"https://pbs.twimg.com/profile_images/522587081034305536/_eKYUDnK_normal.jpeg","summary":"Author of Half-Resurrection Blues: http://bit.ly/halfresblues and Shadowshaper http://bit.ly/shdwshper Lucumí Son of the Sea. Not half & half, all in One.","links":[{"href":"http://ghoststar.net","rel":"me"}],"friendsCount":4638,"followersCount":15334,"listedCount":587,"statusesCount":214189,"twitterTimeZone":"Eastern Time (US & Canada)","verified":false,"utcOffset":"-14400","preferredUsername":"djolder","languages":["en"],"location":{"objectType":"place","displayName":"Brooklyn, NY"},"favoritesCount":11882},"verb":"share","postedTime":"2015-05-08T01:58:25.000Z","generator":{"displayName":"TweetDeck","link":"https://about.twitter.com/products/tweetdeck"},"provider":{"objectType":"service","displayName":"Twitter","link":"http://www.twitter.com"},"link":"http://twitter.com/djolder/statuses/596494331881463808","body":"RT @deray: BREAKING: DOJ to launch federal investigation of @BaltimorePolice #FreddieGray #BaltimoreUprisings http://t.co/DbPdpz0OoR","object":{"id":"tag:search.twitter.com,2005:596483850357907457","objectType":"activity","actor":{"objectType":"person","id":"id:twitter.com:29417304","link":"http://www.twitter.com/deray","displayName":"deray mckesson","postedTime":"2009-04-07T09:38:56.000Z","image":"https://pbs.twimg.com/profile_images/555381462107570176/TBtL-FxK_normal.jpeg","summary":"I will never betray my heart. Curator, connector. TFA alum. Educator. Bowdoin alum. Protestor. snapchat: derayderay\nIG: iamderay\nderay@thisisthemovement.org.","links":[{"href":"http://WeTheProtesters.org","rel":"me"}],"friendsCount":1015,"followersCount":119231,"listedCount":1961,"statusesCount":95748,"twitterTimeZone":"Eastern Time (US & Canada)","verified":false,"utcOffset":"-14400","preferredUsername":"deray","languages":["en"],"favoritesCount":15979},"verb":"post","postedTime":"2015-05-08T01:16:46.000Z","generator":{"displayName":"iOS","link":"http://www.apple.com"},"provider":{"objectType":"service","displayName":"Twitter","link":"http://www.twitter.com"},"link":"http://twitter.com/deray/statuses/596483850357907457","body":"BREAKING: DOJ to launch federal investigation of @BaltimorePolice #FreddieGray #BaltimoreUprisings http://t.co/DbPdpz0OoR","object":{"objectType":"note","id":"object:search.twitter.com,2005:596483850357907457","summary":"BREAKING: DOJ to launch federal investigation of @BaltimorePolice #FreddieGray #BaltimoreUprisings http://t.co/DbPdpz0OoR","link":"http://twitter.com/deray/statuses/596483850357907457","postedTime":"2015-05-08T01:16:46.000Z"},"favoritesCount":158,"twitter_entities":{"hashtags":[{"text":"FreddieGray","indices":[66,78]},{"text":"BaltimoreUprisings","indices":[79,98]}],"trends":[],"urls":[{"url":"http://t.co/DbPdpz0OoR","expanded_url":"http://www.washingtonpost.com/world/national-security/attorney-general-says-she-will-decide-soon-on-a-baltimore-investigation/2015/05/07/b3a422da-f4d4-11e4-b2f3-af5479e6bbdd_story.html?postshare=6051431046998768","display_url":"washingtonpost.com/world/national…","indices":[99,121]}],"user_mentions":[{"screen_name":"BaltimorePolice","name":"Baltimore Police","id":22197119,"id_str":"22197119","indices":[49,65]}],"symbols":[]},"twitter_filter_level":"low","twitter_lang":"en"},"favoritesCount":0,"twitter_entities":{"hashtags":[{"text":"FreddieGray","indices":[77,89]},{"text":"BaltimoreUprisings","indices":[90,109]}],"trends":[],"urls":[{"url":"http://t.co/DbPdpz0OoR","expanded_url":"http://www.washingtonpost.com/world/national-security/attorney-general-says-she-will-decide-soon-on-a-baltimore-investigation/2015/05/07/b3a422da-f4d4-11e4-b2f3-af5479e6bbdd_story.html?postshare=6051431046998768","display_url":"washingtonpost.com/world/national…","indices":[110,132]}],"user_mentions":[{"screen_name":"deray","name":"deray mckesson","id":29417304,"id_str":"29417304","indices":[3,9]},{"screen_name":"BaltimorePolice","name":"Baltimore Police","id":22197119,"id_str":"22197119","indices":[60,76]}],"symbols":[]},"twitter_filter_level":"low","twitter_lang":"en","retweetCount":314,"gnip":{"matching_rules":[{"value":"profile_bounding_box:[-73.968968 40.488377 -73.496968 40.838377] sample:25","tag":null}],"urls":[{"url":"http://t.co/DbPdpz0OoR","expanded_url":"http://www.washingtonpost.com/world/national-security/attorney-general-says-she-will-decide-soon-on-a-baltimore-investigation/2015/05/07/b3a422da-f4d4-11e4-b2f3-af5479e6bbdd_story.html?postshare=6051431046998768","expanded_status":200}],"language":{"value":"en"},"profileLocations":[{"objectType":"place","geo":{"type":"point","coordinates":[-73.94958,40.6501]},"address":{"country":"United States","countryCode":"US","locality":"Brooklyn","region":"New York","subRegion":"Kings County"},"displayName":"Brooklyn, New York, United States"}]}}
{"id":"tag:search.twitter.com,2005:596506016767877121","objectType":"activity","actor":{"objectType":"person","id":"id:twitter.com:245480828","link":"http://www.twitter.com/BMORECOOKIE","displayName":"Bmorecookie4lyfe","postedTime":"2011-01-31T20:02:25.000Z","image":"https://pbs.twimg.com/profile_images/596436795618897921/_H7pyXgc_normal.jpg","summary":"SUPPORTIVE; Realist. No Time For #FakeOnes Period.","links":[{"href":"https://www.facebook.com/pages/Whats-Good-BMORE/641324822565688?fref=nf","rel":"me"}],"friendsCount":98,"followersCount":8,"listedCount":0,"statusesCount":4,"twitterTimeZone":"Central Time (US & Canada)","verified":false,"utcOffset":"-18000","preferredUsername":"BMORECOOKIE","languages":["en"],"location":{"objectType":"place","displayName":"Baltimore, MD "},"favoritesCount":5},"verb":"share","postedTime":"2015-05-08T02:44:51.000Z","generator":{"displayName":"Twitter Web Client","link":"http://twitter.com"},"provider":{"objectType":"service","displayName":"Twitter","link":"http://www.twitter.com"},"link":"http://twitter.com/BMORECOOKIE/statuses/596506016767877121","body":"RT @cbsbaltimore: #CVS vows to rebuild torched stores in #BaltimoreRiots #BaltimoreUprising\nhttp://t.co/6rOT8cNcwA http://t.co/g9ewxE6R52","object":{"id":"tag:search.twitter.com,2005:596502291487662080","objectType":"activity","actor":{"objectType":"person","id":"id:twitter.com:24920395","link":"http://www.twitter.com/cbsbaltimore","displayName":"WJZ | CBS Baltimore","postedTime":"2009-03-17T17:48:44.000Z","image":"https://pbs.twimg.com/profile_images/3158061511/86d9961da9b21db0905136196f20dcc0_normal.jpeg","summary":"The latest #Maryland news, weather, sports and traffic from #WJZ. News tips: 410-578-7568. E-mail: newsroom[at]http://wjz.com. Try our apps.","links":[{"href":"http://www.cbsbaltimore.com","rel":"me"}],"friendsCount":428,"followersCount":76468,"listedCount":1134,"statusesCount":151622,"twitterTimeZone":"Eastern Time (US & Canada)","verified":true,"utcOffset":"-14400","preferredUsername":"cbsbaltimore","languages":["en"],"location":{"objectType":"place","displayName":"Baltimore"},"favoritesCount":575},"verb":"post","postedTime":"2015-05-08T02:30:03.000Z","generator":{"displayName":"TweetDeck","link":"https://about.twitter.com/products/tweetdeck"},"provider":{"objectType":"service","displayName":"Twitter","link":"http://www.twitter.com"},"link":"http://twitter.com/cbsbaltimore/statuses/596502291487662080","body":"#CVS vows to rebuild torched stores in #BaltimoreRiots #BaltimoreUprising\nhttp://t.co/6rOT8cNcwA http://t.co/g9ewxE6R52","object":{"objectType":"note","id":"object:search.twitter.com,2005:596502291487662080","summary":"#CVS vows to rebuild torched stores in #BaltimoreRiots #BaltimoreUprising\nhttp://t.co/6rOT8cNcwA http://t.co/g9ewxE6R52","link":"http://twitter.com/cbsbaltimore/statuses/596502291487662080","postedTime":"2015-05-08T02:30:03.000Z"},"favoritesCount":1,"twitter_entities":{"hashtags":[{"text":"CVS","indices":[0,4]},{"text":"BaltimoreRiots","indices":[39,54]},{"text":"BaltimoreUprising","indices":[55,73]}],"trends":[],"urls":[{"url":"http://t.co/6rOT8cNcwA","expanded_url":"http://cbsloc.al/1P0ZNsv","display_url":"cbsloc.al/1P0ZNsv","indices":[74,96]}],"user_mentions":[],"symbols":[],"media":[{"id":596383273976213505,"id_str":"596383273976213505","indices":[97,119],"media_url":"http://pbs.twimg.com/media/CEbHbYtWMAEFaBh.jpg","media_url_https":"https://pbs.twimg.com/media/CEbHbYtWMAEFaBh.jpg","url":"http://t.co/g9ewxE6R52","display_url":"pic.twitter.com/g9ewxE6R52","expanded_url":"http://twitter.com/cbsbaltimore/status/596502291487662080/photo/1","type":"photo","sizes":{"large":{"w":620,"h":349,"resize":"fit"},"thumb":{"w":150,"h":150,"resize":"crop"},"small":{"w":340,"h":191,"resize":"fit"},"medium":{"w":600,"h":337,"resize":"fit"}}}]},"twitter_extended_entities":{"media":[{"id":596383273976213505,"id_str":"596383273976213505","indices":[97,119],"media_url":"http://pbs.twimg.com/media/CEbHbYtWMAEFaBh.jpg","media_url_https":"https://pbs.twimg.com/media/CEbHbYtWMAEFaBh.jpg","url":"http://t.co/g9ewxE6R52","display_url":"pic.twitter.com/g9ewxE6R52","expanded_url":"http://twitter.com/cbsbaltimore/status/596502291487662080/photo/1","type":"photo","sizes":{"large":{"w":620,"h":349,"resize":"fit"},"thumb":{"w":150,"h":150,"resize":"crop"},"small":{"w":340,"h":191,"resize":"fit"},"medium":{"w":600,"h":337,"resize":"fit"}}}]},"twitter_filter_level":"low","twitter_lang":"en"},"favoritesCount":0,"twitter_entities":{"hashtags":[{"text":"CVS","indices":[18,22]},{"text":"BaltimoreRiots","indices":[57,72]},{"text":"BaltimoreUprising","indices":[73,91]}],"trends":[],"urls":[{"url":"http://t.co/6rOT8cNcwA","expanded_url":"http://cbsloc.al/1P0ZNsv","display_url":"cbsloc.al/1P0ZNsv","indices":[92,114]}],"user_mentions":[{"screen_name":"cbsbaltimore","name":"WJZ | CBS Baltimore","id":24920395,"id_str":"24920395","indices":[3,16]}],"symbols":[],"media":[{"id":596383273976213505,"id_str":"596383273976213505","indices":[115,137],"media_url":"http://pbs.twimg.com/media/CEbHbYtWMAEFaBh.jpg","media_url_https":"https://pbs.twimg.com/media/CEbHbYtWMAEFaBh.jpg","url":"http://t.co/g9ewxE6R52","display_url":"pic.twitter.com/g9ewxE6R52","expanded_url":"http://twitter.com/cbsbaltimore/status/596502291487662080/photo/1","type":"photo","sizes":{"large":{"w":620,"h":349,"resize":"fit"},"thumb":{"w":150,"h":150,"resize":"crop"},"small":{"w":340,"h":191,"resize":"fit"},"medium":{"w":600,"h":337,"resize":"fit"}},"source_status_id":596502291487662080,"source_status_id_str":"596502291487662080"}]},"twitter_extended_entities":{"media":[{"id":596383273976213505,"id_str":"596383273976213505","indices":[115,137],"media_url":"http://pbs.twimg.com/media/CEbHbYtWMAEFaBh.jpg","media_url_https":"https://pbs.twimg.com/media/CEbHbYtWMAEFaBh.jpg","url":"http://t.co/g9ewxE6R52","display_url":"pic.twitter.com/g9ewxE6R52","expanded_url":"http://twitter.com/cbsbaltimore/status/596502291487662080/photo/1","type":"photo","sizes":{"large":{"w":620,"h":349,"resize":"fit"},"thumb":{"w":150,"h":150,"resize":"crop"},"small":{"w":340,"h":191,"resize":"fit"},"medium":{"w":600,"h":337,"resize":"fit"}},"source_status_id":596502291487662080,"source_status_id_str":"596502291487662080"}]},"twitter_filter_level":"low","twitter_lang":"en","retweetCount":2,"gnip":{"matching_rules":[{"value":"profile_bounding_box:[-77.027094 39.094659 -76.567094 39.444659] sample:25","tag":null}],"urls":[{"url":"http://t.co/6rOT8cNcwA","expanded_url":"http://baltimore.cbslocal.com/2015/05/06/cvs-announces-it-will-rebuild-burned-stores/","expanded_status":200},{"url":"http://t.co/g9ewxE6R52","expanded_url":"http://twitter.com/cbsbaltimore/status/596502291487662080/photo/1","expanded_status":200}],"language":{"value":"en"},"profileLocations":[{"objectType":"place","geo":{"type":"point","coordinates":[-76.61219,39.29038]},"address":{"country":"United States","countryCode":"US","locality":"Baltimore","region":"Maryland","subRegion":"City of Baltimore"},"displayName":"Baltimore, Maryland, United States"}]}}
