{"id":"tag:search.twitter.com,2005:596375420502609920","objectType":"activity","actor":{"objectType":"person","id":"id:twitter.com:81240509","link":"http://www.twitter.com/seanjjordan","displayName":"Sean Jordan","postedTime":"2009-10-10T00:31:28.000Z","image":"https://pbs.twimg.com/profile_images/560208486189920256/IBNuYCy5_normal.jpeg","summary":"I read. I write. I think. I believe #BlackLivesMatter.\n\nRetweets/follows do not indicate agreement or endorsement.","links":[{"href":"https://twitter.com/seanjjordan","rel":"me"}],"friendsCount":406,"followersCount":3523,"listedCount":151,"statusesCount":29543,"twitterTimeZone":"Central Time (US & Canada)","verified":false,"utcOffset":"-18000","preferredUsername":"seanjjordan","languages":["en"],"location":{"objectType":"place","displayName":"St. Louis, MO"},"favoritesCount":56},"verb":"share","postedTime":"2015-05-07T18:05:55.000Z","generator":{"displayName":"Twitter Web Client","link":"http://twitter.com"},"provider":{"objectType":"service","displayName":"Twitter","link":"http://www.twitter.com"},"link":"http://twitter.com/seanjjordan/statuses/596375420502609920","body":"RT @POPSspotSports: 243 page #deflategate report marks official end to calling #Ferguson DOJ Report \"exhaustive\" Add #tedwells 2 #FreddieGr…","object":{"id":"tag:search.twitter.com,2005:596335093205049346","objectType":"activity","actor":{"objectType":"person","id":"id:twitter.com:728604440","link":"http://www.twitter.com/POPSspotSports","displayName":"Chuck_MODI","postedTime":"2012-07-31T15:17:49.000Z","image":"https://pbs.twimg.com/profile_images/567537006000234498/kUakCz9q_normal.jpeg","summary":"Justice 4 Mike Brown and beyond. Exposes Power, Oppression & Privilege in Sport @ http://popsspot.com","links":[{"href":"http://www.popsspot.com","rel":"me"}],"friendsCount":2776,"followersCount":4541,"listedCount":147,"statusesCount":10603,"twitterTimeZone":"Eastern Time (US & Canada)","verified":false,"utcOffset":"-14400","preferredUsername":"POPSspotSports","languages":["en"],"location":{"objectType":"place","displayName":"DC Area"},"favoritesCount":1808},"verb":"post","postedTime":"2015-05-07T15:25:40.000Z","generator":{"displayName":"Twitter for iPhone","link":"http://twitter.com/download/iphone"},"provider":{"objectType":"service","displayName":"Twitter","link":"http://www.twitter.com"},"link":"http://twitter.com/POPSspotSports/statuses/596335093205049346","body":"243 page #deflategate report marks official end to calling #Ferguson DOJ Report \"exhaustive\" Add #tedwells 2 #FreddieGray #MarilynMosby team","object":{"objectType":"note","id":"object:search.twitter.com,2005:596335093205049346","summary":"243 page #deflategate report marks official end to calling #Ferguson DOJ Report \"exhaustive\" Add #tedwells 2 #FreddieGray #MarilynMosby team","link":"http://twitter.com/POPSspotSports/statuses/596335093205049346","postedTime":"2015-05-07T15:25:40.000Z"},"favoritesCount":1,"twitter_entities":{"hashtags":[{"text":"deflategate","indices":[9,21]},{"text":"Ferguson","indices":[59,68]},{"text":"tedwells","indices":[97,106]},{"text":"FreddieGray","indices":[109,121]},{"text":"MarilynMosby","indices":[122,135]}],"trends":[],"urls":[],"user_mentions":[],"symbols":[]},"twitter_filter_level":"low","twitter_lang":"en"},"favoritesCount":0,"twitter_entities":{"hashtags":[{"text":"deflategate","indices":[29,41]},{"text":"Ferguson","indices":[79,88]},{"text":"tedwells","indices":[117,126]},{"text":"FreddieGray","indices":[129,140]},{"text":"MarilynMosby","indices":[139,140]}],"trends":[],"urls":[],"user_mentions":[{"screen_name":"POPSspotSports","name":"Chuck_MODI","id":728604440,"id_str":"728604440","indices":[3,18]}],"symbols":[]},"twitter_filter_level":"low","twitter_lang":"en","retweetCount":3,"gnip":{"matching_rules":[{"value":"profile_bounding_box:[-90.549225 38.396171 -90.091225 38.746171] sample:25","tag":null}],"language":{"value":"en"},"profileLocations":[{"objectType":"place","geo":{"type":"point","coordinates":[-90.19789,38.62727]},"address":{"country":"United States","countryCode":"US","locality":"St. Louis","region":"Missouri","subRegion":"City of Saint Louis"},"displayName":"St. Louis, Missouri, United States"}]}}
